{"frames": {

"brzda-pred.png":
{
	"frame": {"x":447,"y":46,"w":45,"h":41},
	"rotated": false,
	"trimmed": true,
	"spriteSourceSize": {"x":358,"y":155,"w":45,"h":41},
	"sourceSize": {"w":480,"h":270}
},
"brzda-zad.png":
{
	"frame": {"x":447,"y":2,"w":45,"h":42},
	"rotated": false,
	"trimmed": true,
	"spriteSourceSize": {"x":78,"y":155,"w":45,"h":42},
	"sourceSize": {"w":480,"h":270}
},
"d.png":
{
	"frame": {"x":2,"y":123,"w":439,"h":150},
	"rotated": false,
	"trimmed": true,
	"spriteSourceSize": {"x":21,"y":47,"w":439,"h":150},
	"sourceSize": {"w":480,"h":270}
},
"dielis.png":
{
	"frame": {"x":2,"y":578,"w":404,"h":60},
	"rotated": false,
	"trimmed": true,
	"spriteSourceSize": {"x":57,"y":137,"w":404,"h":60},
	"sourceSize": {"w":480,"h":270}
},
"dielis2.png":
{
	"frame": {"x":2,"y":2,"w":443,"h":119},
	"rotated": false,
	"trimmed": true,
	"spriteSourceSize": {"x":14,"y":55,"w":443,"h":119},
	"sourceSize": {"w":480,"h":270}
},
"exhaust.png":
{
	"frame": {"x":257,"y":640,"w":71,"h":19},
	"rotated": false,
	"trimmed": false,
	"spriteSourceSize": {"x":0,"y":0,"w":71,"h":19},
	"sourceSize": {"w":71,"h":19}
},
"glass.png":
{
	"frame": {"x":257,"y":662,"w":253,"h":58},
	"rotated": false,
	"trimmed": true,
	"spriteSourceSize": {"x":78,"y":56,"w":253,"h":58},
	"sourceSize": {"w":480,"h":270}
},
"glossy_add.png":
{
	"frame": {"x":2,"y":427,"w":436,"h":149},
	"rotated": false,
	"trimmed": true,
	"spriteSourceSize": {"x":23,"y":47,"w":436,"h":149},
	"sourceSize": {"w":480,"h":270}
},
"glossy_add1.png":
{
	"frame": {"x":2,"y":275,"w":439,"h":150},
	"rotated": false,
	"trimmed": true,
	"spriteSourceSize": {"x":21,"y":47,"w":439,"h":150},
	"sourceSize": {"w":480,"h":270}
},
"interior.png":
{
	"frame": {"x":2,"y":640,"w":253,"h":99},
	"rotated": false,
	"trimmed": true,
	"spriteSourceSize": {"x":79,"y":61,"w":253,"h":99},
	"sourceSize": {"w":480,"h":270}
},
"kolesa_hviezda.png":
{
	"frame": {"x":443,"y":123,"w":64,"h":61},
	"rotated": false,
	"trimmed": true,
	"spriteSourceSize": {"x":40,"y":8,"w":64,"h":61},
	"sourceSize": {"w":144,"h":81}
},
"koleso-pred.png":
{
	"frame": {"x":408,"y":578,"w":83,"h":82},
	"rotated": false,
	"trimmed": true,
	"spriteSourceSize": {"x":338,"y":131,"w":83,"h":82},
	"sourceSize": {"w":480,"h":270}
},
"koleso-zad.png":
{
	"frame": {"x":2,"y":799,"w":83,"h":82},
	"rotated": false,
	"trimmed": true,
	"spriteSourceSize": {"x":62,"y":131,"w":83,"h":82},
	"sourceSize": {"w":480,"h":270}
},
"shadow.png":
{
	"frame": {"x":257,"y":722,"w":237,"h":75},
	"rotated": false,
	"trimmed": true,
	"spriteSourceSize": {"x":0,"y":4,"w":237,"h":75},
	"sourceSize": {"w":240,"h":82}
},
"void.png":
{
	"frame": {"x":494,"y":2,"w":3,"h":3},
	"rotated": false,
	"trimmed": true,
	"spriteSourceSize": {"x":0,"y":0,"w":3,"h":3},
	"sourceSize": {"w":1,"h":1}
}},
"meta": {
	"app": "http://www.codeandweb.com/texturepacker",
	"version": "1.0",
	"image": "car1.png",
	"format": "RGBA8888",
	"size": {"w":512,"h":1024},
	"scale": "0.5",
	"smartupdate": "$TexturePacker:SmartUpdate:0aa0cca33824a204e02f366075a17214:d59aa1828c269f9954d111e75ac0eca5:17f2c87b30dbfbd8110e2b613b5f5590$"
}
}
